jupyter_openwebui/__init__.py
jupyter_openwebui/_version.py
jupyter_openwebui-0.2.1.data/data/share/jupyter/labextensions/jupyter-openwebui/package.json
jupyter_openwebui-0.2.1.data/data/share/jupyter/labextensions/jupyter-openwebui/schemas/jupyter-openwebui/package.json.orig
jupyter_openwebui-0.2.1.data/data/share/jupyter/labextensions/jupyter-openwebui/schemas/jupyter-openwebui/plugin.json
jupyter_openwebui-0.2.1.data/data/share/jupyter/labextensions/jupyter-openwebui/static/497.797b871b55f326888583.js
jupyter_openwebui-0.2.1.data/data/share/jupyter/labextensions/jupyter-openwebui/static/728.ac077b671d182eaac893.js
jupyter_openwebui-0.2.1.data/data/share/jupyter/labextensions/jupyter-openwebui/static/remoteEntry.338c420418ae8c0fcfc4.js
jupyter_openwebui-0.2.1.data/data/share/jupyter/labextensions/jupyter-openwebui/static/style.js
jupyter_openwebui-0.2.1.data/data/share/jupyter/labextensions/jupyter-openwebui/static/third-party-licenses.json
jupyter_openwebui-0.2.1.data/data/share/jupyter/labextensions/jupyter-openwebui/install.json
jupyter_openwebui-0.2.1.dist-info/METADATA
jupyter_openwebui-0.2.1.dist-info/WHEEL
jupyter_openwebui-0.2.1.dist-info/licenses/LICENSE
jupyter_openwebui-0.2.1.dist-info/RECORD
