Metadata-Version: 2.4
Name: jupyter_openwebui
Version: 0.2.1
Summary: Open webui frontend to JupyterLab extension.
Project-URL: Homepage, https://github.com/felix5572/jupyter-openwebui.git
Project-URL: Bug Tracker, https://github.com/felix5572/jupyter-openwebui.git/issues
Project-URL: Repository, https://github.com/felix5572/jupyter-openwebui.git.git
Author-email: felix5572 <yfb222333@gmail.com>
License: BSD 3-Clause License
License-File: LICENSE
Keywords: jupyter,jupyterlab,jupyterlab-extension
Classifier: Framework :: Jupyter
Classifier: Framework :: Jupyter :: JupyterLab
Classifier: Framework :: Jupyter :: JupyterLab :: 4
Classifier: Framework :: Jupyter :: JupyterLab :: Extensions
Classifier: Framework :: Jupyter :: JupyterLab :: Extensions :: Prebuilt
Classifier: License :: OSI Approved :: BSD License
Classifier: Programming Language :: Python
Classifier: Programming Language :: Python :: 3
Classifier: Programming Language :: Python :: 3.9
Classifier: Programming Language :: Python :: 3.10
Classifier: Programming Language :: Python :: 3.11
Classifier: Programming Language :: Python :: 3.12
Classifier: Programming Language :: Python :: 3.13
Requires-Python: >=3.9
